Workbook

Sheet Dashboard
A1: JOB SEARCH DASHBOARD
A2: Every figure below updates automatically from the Applications tab (rows 3–502).
A4: PIPELINE FUNNEL | E4: WHAT'S ACTUALLY WORKING
A5: Stage | B5: Count | C5: % of Applied | E5: Source | F5: Applied | G5: Interviews
A6: Applications submitted | B6: =COUNT(Applications!$H$3:$H$502) | E6: LinkedIn | F6: =COUNTIFS(Applications!$F$3:$F$502,$E6,Applications!$H$3:$H$502,">0") | G6: =SUMPRODUCT((Applications!$F$3:$F$502=$E6)*((Applications!$I$3:$I$502="Interview")+(Applications!$I$3:$I$502="Final Round")+(Applications!$I$3:$I$502="Offer")))
A7: Reached phone screen | B7: =COUNTIF(Applications!$I$3:$I$502,"Phone Screen")+COUNTIF(Applications!$I$3:$I$502,"Interview")+COUNTIF(Applications!$I$3:$I$502,"Final Round")+COUNTIF(Applications!$I$3:$I$502,"Offer") | C7: =IFERROR(B7/$B$6,"") | E7: Company Site | F7: =COUNTIFS(Applications!$F$3:$F$502,$E7,Applications!$H$3:$H$502,">0") | G7: =SUMPRODUCT((Applications!$F$3:$F$502=$E7)*((Applications!$I$3:$I$502="Interview")+(Applications!$I$3:$I$502="Final Round")+(Applications!$I$3:$I$502="Offer")))
A8: Reached interview | B8: =COUNTIF(Applications!$I$3:$I$502,"Interview")+COUNTIF(Applications!$I$3:$I$502,"Final Round")+COUNTIF(Applications!$I$3:$I$502,"Offer") | C8: =IFERROR(B8/$B$6,"") | E8: Referral | F8: =COUNTIFS(Applications!$F$3:$F$502,$E8,Applications!$H$3:$H$502,">0") | G8: =SUMPRODUCT((Applications!$F$3:$F$502=$E8)*((Applications!$I$3:$I$502="Interview")+(Applications!$I$3:$I$502="Final Round")+(Applications!$I$3:$I$502="Offer")))
A9: Reached final round | B9: =COUNTIF(Applications!$I$3:$I$502,"Final Round")+COUNTIF(Applications!$I$3:$I$502,"Offer") | C9: =IFERROR(B9/$B$6,"") | E9: Recruiter | F9: =COUNTIFS(Applications!$F$3:$F$502,$E9,Applications!$H$3:$H$502,">0") | G9: =SUMPRODUCT((Applications!$F$3:$F$502=$E9)*((Applications!$I$3:$I$502="Interview")+(Applications!$I$3:$I$502="Final Round")+(Applications!$I$3:$I$502="Offer")))
A10: Offers received | B10: =COUNTIF(Applications!$I$3:$I$502,"Offer") | C10: =IFERROR(B10/$B$6,"") | E10: Indeed | F10: =COUNTIFS(Applications!$F$3:$F$502,$E10,Applications!$H$3:$H$502,">0") | G10: =SUMPRODUCT((Applications!$F$3:$F$502=$E10)*((Applications!$I$3:$I$502="Interview")+(Applications!$I$3:$I$502="Final Round")+(Applications!$I$3:$I$502="Offer")))
E11: Glassdoor | F11: =COUNTIFS(Applications!$F$3:$F$502,$E11,Applications!$H$3:$H$502,">0") | G11: =SUMPRODUCT((Applications!$F$3:$F$502=$E11)*((Applications!$I$3:$I$502="Interview")+(Applications!$I$3:$I$502="Final Round")+(Applications!$I$3:$I$502="Offer")))
A12: WHERE THINGS STAND | E12: Job Board | F12: =COUNTIFS(Applications!$F$3:$F$502,$E12,Applications!$H$3:$H$502,">0") | G12: =SUMPRODUCT((Applications!$F$3:$F$502=$E12)*((Applications!$I$3:$I$502="Interview")+(Applications!$I$3:$I$502="Final Round")+(Applications!$I$3:$I$502="Offer")))
A13: Still active (no outcome yet) | B13: =SUMPRODUCT((Applications!$H$3:$H$502<>"")*(Applications!$J$3:$J$502="")) | E13: Networking | F13: =COUNTIFS(Applications!$F$3:$F$502,$E13,Applications!$H$3:$H$502,">0") | G13: =SUMPRODUCT((Applications!$F$3:$F$502=$E13)*((Applications!$I$3:$I$502="Interview")+(Applications!$I$3:$I$502="Final Round")+(Applications!$I$3:$I$502="Offer")))
A14: Not applied yet | B14: =COUNTIF(Applications!$I$3:$I$502,"To Apply") | E14: Other | F14: =COUNTIFS(Applications!$F$3:$F$502,$E14,Applications!$H$3:$H$502,">0") | G14: =SUMPRODUCT((Applications!$F$3:$F$502=$E14)*((Applications!$I$3:$I$502="Interview")+(Applications!$I$3:$I$502="Final Round")+(Applications!$I$3:$I$502="Offer")))
A15: Rejected | B15: =COUNTIF(Applications!$J$3:$J$502,"Rejected")
A16: Ghosted | B16: =COUNTIF(Applications!$J$3:$J$502,"Ghosted")
A17: Withdrawn | B17: =COUNTIF(Applications!$J$3:$J$502,"Withdrawn") | E17: HOW TO USE THIS TRACKER
A18: Offers accepted | B18: =COUNTIF(Applications!$J$3:$J$502,"Offer Accepted") | E18: 1. Add one row per role on the Applications tab. Row 3 is an example — overwrite it.
A19: Total roles tracked | B19: =COUNTA(Applications!$A$3:$A$502) | E19: 2. Stage = the furthest point you have reached. Move it forward as you progress.
E20: 3. Outcome = only fill this in when a role ends. Blank means it is still live.
A21: ACTION NEEDED | E21: 4. Days Since Applied fills itself in. It turns orange after 14 days with no outcome.
A22: Applied in the last 7 days | B22: =COUNTIFS(Applications!$H$3:$H$502,">="&TODAY()-7) | E22: 5. A Follow-Up Date turns red on the day it is due, so filter that column to plan your week.
A23: Applied in the last 30 days | B23: =COUNTIFS(Applications!$H$3:$H$502,">="&TODAY()-30) | E23: 6. Dropdown options live on the Lists tab — add your own values there any time.
A24: Follow-ups due or overdue | B24: =SUMPRODUCT((Applications!$N$3:$N$502<>"")*(Applications!$N$3:$N$502<=TODAY())*(Applications!$J$3:$J$502="")) | E24: 7. Use the filter arrows on row 2 to slice by stage, source, or priority.
A25: Waiting 14+ days with no reply | B25: =SUMPRODUCT((Applications!$H$3:$H$502<>"")*(Applications!$H$3:$H$502<TODAY()-14)*(Applications!$J$3:$J$502="")*(Applications!$I$3:$I$502="Applied"))
A26: High-priority roles still open | B26: =SUMPRODUCT((Applications!$R$3:$R$502="High")*(Applications!$J$3:$J$502=""))
A30: Note: dashboard formulas cover Applications rows 3–502. Extend the ranges if you add more than 500 roles.

Sheet Applications
A1: JOB APPLICATION TRACKER | E1: Fill in every column except Days Since Applied (grey, auto-calculated). Row 3 is an example — overwrite or delete it.
A2: Company | B2: Role / Title | C2: Location | D2: Work Setup | E2: Salary / Comp | F2: Source | G2: Job Link | H2: Date Applied | I2: Stage | J2: Outcome | K2: Days Since Applied | L2: Last Contact | M2: Next Action | N2: Follow-Up Date | O2: Contact Name | P2: Contact Email | Q2: Resume Version | R2: Priority | S2: Notes
A3: Detajl | B3: Civil Engineer – Designer (traffic/municipal infrastructure) | C3: Vipava, SI | F3: Job Board | H3: 46231 | I3: Applied | K3: =IF($H3="","",TODAY()-$H3) | O3: Marko Lavrenčič | P3: marko@detajl.eu | Q3: slovenia/2026_07_28_detajl_marko_lavrencic | R3: Medium | S3: Reg. RC23034. No driving license (candidate lacks one) — omitted, not raised.
A4: Energetika Ljubljana (JHL) | B4: Planning Development Solutions (energy systems – heat/gas supply) | C4: Ljubljana, SI | F4: Job Board | H4: 46231 | I4: Applied | K4: =IF($H4="","",TODAY()-$H4) | O4: Janka Likosar | P4: kadri-jpe@jhl.si | Q4: slovenia/2026_07_28_energetika_ljubljana_janka_likosar | R4: Medium | S4: Reg. RD22005. Domain stretch (energy vs. BIM/civil) — leans on MEP coordination + energy-mgmt coursework.
A5: Hidrotehnik | B5: Design Engineer – Water Management | C5: Ljubljana, SI | D5: Hybrid | F5: Job Board | H5: 46231 | I5: Applied | K5: =IF($H5="","",TODAY()-$H5) | O5: Matthew B. | P5: info@hidrotehnik.si | Q5: slovenia/2026_07_28_hidrotehnik_matthew_b | R5: Medium | S5: Reg. RD21686. Honest about <2yr experience gap and A1 Slovene vs. required fluent.
A6: Atrij | B6: Speculative – BIM/digitalization pitch (advertised role: building-structures drafter) | C6: Odranci, SI | F6: Job Board | H6: 46231 | I6: Applied | K6: =IF($H6="","",TODAY()-$H6) | O6: Nina Kolarič Tibaut | P6: atrij@atrij.si | Q6: slovenia/2026_07_28_atrij_nina_kolaric_tibaut | R6: Low | S6: Reg. RC87935 (advertised role skipped, not a match). Speculative pitch — 10-person firm, no existing BIM function.
A7: RMB Modul | B7: Cost Estimation / 5D Quantity Take-off | C7: Velika Polana, SI | F7: Job Board | H7: 46231 | I7: Applied | K7: =IF($H7="","",TODAY()-$H7) | O7: Stojan Špitalar | P7: stojan@rmbmodul.com | Q7: slovenia/2026_07_28_rmb_modul_stojan_spitalar | R7: Medium | S7: Reg. PZ46034. Strong content match (5D QTO). Honest that candidate has zero German (posting states mandatory).
A8: HNG d.o.o. | B8: Student Work – Inventory of Water Facilities, Devices & Arrangements | C8: Mengeš, SI | D8: Hybrid | F8: Job Board | G8: https://popr.uni-lj.si/student/employers.html?employer=441557&page=employer | H8: 46231 | I8: Applied | K8: =IF($H8="","",TODAY()-$H8) | Q8: slovenia/2026_07_28_hng_doo | R8: Medium | S8: Student-work listing via UL popr portal (no email; apply through portal). Surfaced real ArcGIS/hydrology coursework.
A9: Zagožen d.o.o. | B9: Utility/Civil/Mechanical Engineer – utility infrastructure | C9: Žalec, SI | F9: Job Board | G9: https://popr.uni-lj.si/student/employers.html?employer=441554&page=employer | H9: 46231 | I9: Applied | K9: =IF($H9="","",TODAY()-$H9) | O9: Kadrovska služba (HR) | Q9: slovenia/2026_07_28_zagozen_doo | R9: High | S9: Full-time, explicitly targets 0-2 yrs experience. Water/sewage infrastructure — strong natural fit. UL popr portal.
A10: Saning d.o.o. | B10: Speculative – BIM/digitalization pitch (advertised role: site operations manager) | C10: Kranj, SI | F10: Job Board | G10: https://popr.uni-lj.si/student/employers.html?employer=441546&page=employer | H10: 46231 | I10: Applied | K10: =IF($H10="","",TODAY()-$H10) | Q10: slovenia/2026_07_28_saning_doo | R10: Low | S10: Advertised role skipped as mismatch. Speculative pitch — no existing BIM function despite larger multi-country group.
A11: DOTES d.o.o. | B11: Speculative – BIM/digitalization pitch (advertised: scholarship for enrolled students) | C11: Dolenja vas, SI | F11: Job Board | G11: https://popr.uni-lj.si/student/employers.html?employer=441544&page=employer | H11: 46231 | I11: Applied | K11: =IF($H11="","",TODAY()-$H11) | P11: info@dotes.si | Q11: slovenia/2026_07_28_dotes_doo | R11: Low | S11: Scholarship required proof of enrollment — ineligible post-graduation. Redirected to speculative BIM pitch, hooked on their new 3D-visualization service.
A12: IKB d.o.o. | B12: Civil Engineer, Designer (Building Structures / BIM A+) | C12: Ljubljana, SI | F12: Job Board | H12: 46231 | I12: Applied | K12: =IF($H12="","",TODAY()-$H12) | O12: Dejan Batistič | P12: dejan@ikb.si | Q12: slovenia/2026_07_28_ikb_dejan_batistic | R12: High | S12: Near-exact match — posting names 'BIM A+' by name as a qualifying major, which is the candidate's literal degree.
A13: Protim Ržišnik Perc | B13: Mechanical Installation Designer (sprinkler systems) | C13: Šenčur, SI | D13: Hybrid | F13: Job Board | H13: 46232 | I13: Applied | K13: =IF($H13="","",TODAY()-$H13) | O13: Tina Brojan | P13: tina.brojan@rp.si | Q13: slovenia/2026_07_29_protim_rzisnik_perc_tina_brojan | R13: Medium | S13: Strong BIM/MEP overlap but formal degree mismatch (mechanical vs. civil) — addressed honestly.
A14: BOSON d.o.o. | B14: Civil Engineer – Designer for Building Construction | C14: Ljubljana, SI | D14: On-site | F14: Job Board | H14: 46232 | I14: Applied | K14: =IF($H14="","",TODAY()-$H14) | O14: Dr. Aljoša J. Tahir | P14: zaposlitev@boson.si | Q14: slovenia/2026_07_29_boson_aljosa_tahir | R14: Medium | S14: Same role type as Detajl (traffic/municipal infrastructure design).
A15: Standard d.o.o. | B15: Designer – Civil Construction (infrastructure facilities) | C15: Ljubljana, SI | F15: Job Board | H15: 46232 | I15: Applied | K15: =IF($H15="","",TODAY()-$H15) | O15: Peter Berglez | P15: peter.berglez@standard.si | Q15: slovenia/2026_07_29_standard_peter_berglez | R15: Medium | S15: Modest requirements (AutoCAD, MS Office); experience only 'desirable'. Approachable fit.
A16: LynxCraft | B16: Follow-up – student work (no formal posting) | C16: Ljubljana, SI | F16: Networking | H16: 46232 | I16: Applied | J16: Rejected | K16: =IF($H16="","",TODAY()-$H16) | O16: Iztok Šušteršič | P16: iztok@lynx-craft.com | Q16: slovenia/2026_07_29_lynxcraft_iztok_sustersic | R16: High | S16: Warm contact — interviewed March 2026; founder said 'collaborate once funded'. Follow-up re: graduation + ~2mo student availability.
A17: Kolektor Construction | B17: Outreach – student work, intro to other departments (no formal posting) | C17: Logatec, SI | F17: Networking | H17: 46232 | I17: Applied | K17: =IF($H17="","",TODAY()-$H17) | O17: Metod Gaber | P17: Metod.Gaber@kolektor.com | Q17: slovenia/2026_07_29_kolektor_construction_metod_gaber | R17: High | S17: Very warm personal contact; Metod is an active BIM figure at Kolektor (BIMpogovori podcast). Asked for dept. introductions + Slovene commitment (fluent within 2 years).
A18: DCT Group | B18: BIM Coordinator (Porto office) | C18: Porto, PT | D18: Hybrid | F18: Company Site | H18: 46234 | I18: Applied | K18: =IF($H18="","",TODAY()-$H18) | Q18: portugal/2026_07_31_dct | R18: High | S18: Strong match — federated model/clash detection/5D QTO/scan-to-BIM point-cloud all directly relevant. Applied via careers page; open to EU relocation.
A19: Sweco | B19: Junior Systems Engineer (Information Engineering) | C19: Netherlands | D19: Hybrid | F19: Company Site | H19: 46236 | I19: Applied | K19: =IF($H19="","",TODAY()-$H19) | O19: David Peters | P19: david.peters@sweco.nl | Q19: netherlands/2026_08_02_sweco_david_peters | R19: Medium | S19: 0-3 yrs target. Strong conceptual fit (requirements/traceability/verification). Honest that candidate has zero Dutch vs. required 'at least C1'.
A20: Sweco | B20: Junior BIM Modeller – Urban Projects Alkmaar | C20: Alkmaar, NL | D20: Hybrid | F20: Company Site | G20: https://www.sweco.nl/solliciteren/?vacancy=39969 | H20: 46236 | I20: Applied | J20: Rejected | K20: =IF($H20="","",TODAY()-$H20) | O20: Bart Witte | P20: bart.witte@sweco.nl | Q20: netherlands/2026_08_02_sweco_bart_witte | R20: Medium | S20: Best skills-match posting overall (Revit/AutoCAD modelling). Same Dutch C1 gap as the Systems Engineer role.
A21: Sweco | B21: AI and BIM Subject Manager / Head of Department (Rail, Bridge & Tunnel) | C21: Ørestad (Copenhagen), DK | F21: Company Site | H21: 46237 | I21: Applied | K21: =IF($H21="","",TODAY()-$H21) | Q21: denmark/2026_08_03_sweco_head_of_bim_ai | R21: Low | S21: Long-shot per user request — senior Head of Department role requiring solid infrastructure/leadership experience candidate lacks. Leans on BIMGraphExplorer (LLM agent) + Autodesk ACC as genuine overlap. No named contact given.
A22: Sweco | B22: BIM Coordinator – Technical Building Equipment (m/f/x), Job No. S2921 | C22: Munich, DE | F22: Company Site | G22: https://www.sweco-services.de/bms.nsf/Bewerbung?openform&job=S2921 | H22: 46237 | I22: Applied | K22: =IF($H22="","",TODAY()-$H22) | Q22: germany/2026_08_03_sweco_munich_bim_coordinator | R22: Low | S22: Stacked gaps: several years experience required, LINEAR/ALPI software not held, German mandatory (candidate has none). Applied anyway, honest about all three. First German-market CV variant (DOB/nationality added, MM.YYYY dates, no photo — flagged not fabricated).
A23: Bayards Aluminium Solutions | B23: Cost Proposal Engineer – Aluminium Solutions | C23: Nieuw-Lekkerland, NL | F23: Company Site | H23: 46238 | I23: Applied | J23: Rejected | K23: =IF($H23="","",TODAY()-$H23) | P23: work@bayards.com | Q23: netherlands/2026_08_04_bayards | R23: Medium | S23: Strong content match (5D QTO coursework, Contract Management internship pricing/contract review). Honest that candidate has zero Dutch vs. required proficiency in both Dutch and English.
A24: Arup | B24: Junior Bridge Engineer (Bridge & Civil Structures), Job AMS000074 | C24: Amsterdam, NL | D24: Hybrid | F24: Company Site | H24: 46238 | I24: Applied | K24: =IF($H24="","",TODAY()-$H24) | Q24: netherlands/2026_08_04_arup_junior_bridge_engineer | R24: Medium | S24: Junior-friendly seniority fit, but real gaps in FEM/structural calculations (candidate specializes in BIM coordination, not structural analysis) and Dutch B1 (candidate has none). Per user instruction, CV/letter do NOT disclose these gaps — lean only on genuine parametric-design/automation strengths.
A25: Arup | B25: Junior Project Manager – Science, Industry & Technology | C25: Frankfurt, DE | D25: Hybrid | F25: Company Site | H25: 46238 | I25: Applied | K25: =IF($H25="","",TODAY()-$H25) | Q25: germany/2026_08_04_arup_frankfurt_junior_pm | R25: Medium | S25: Junior-friendly (internships/student activities explicitly welcomed). Real gap: "very good German" required, candidate has none. Per updated default, CV/letter do not disclose this gap.
A26: Arup | B26: Assistant Computational Designer – Digital Team | C26: Milan, IT | F26: Company Site | H26: 46238 | I26: Applied | K26: =IF($H26="","",TODAY()-$H26) | Q26: italy/2026_08_04_arup_milan_computational_designer | R26: High | S26: Excellent fit — explicitly welcomes recent graduates, no language gap beyond English, strong overlap on Python/Dynamo/Revit/Git/AI-agent work and GIS (ArcGIS). No major mismatch to flag.
A27: Arup | B27: Open Application – Design Manager, Private & Government Property, Job AMS000091 | C27: Amsterdam, NL | F27: Company Site | G27: https://jobs.arup.com/jobs/33871/other-jobs-matching/location-only | H27: 46238 | I27: Applied | K27: =IF($H27="","",TODAY()-$H27) | Q27: netherlands/2026_08_04_arup_amsterdam_design_manager | R27: Medium | S27: Open solicitation (not a live vacancy), junior-friendly. Real gap: fluent Dutch required, candidate has none. Per updated default, CV/letter do not disclose this gap.
A28: Arup | B28: Open Application – Project Management, Science & Industry, Job AMS000094 | C28: Amsterdam, NL | F28: Company Site | G28: https://jobs.arup.com/jobs/33686/other-jobs-matching/location-only | H28: 46238 | I28: Applied | K28: =IF($H28="","",TODAY()-$H28) | Q28: netherlands/2026_08_04_arup_amsterdam_science_industry_pm | R28: Medium | S28: Open solicitation (not a live vacancy), junior-friendly, same shape as the Design Manager open application. Real gap: fluent Dutch required, candidate has none — not disclosed per updated default.
A29: Arup | B29: Open Application – Project Management, Technology / Data Centers, Job AMS000092 | C29: Amsterdam, NL | F29: Company Site | G29: https://jobs.arup.com/jobs/33870/other-jobs-matching/location-only | H29: 46238 | I29: Applied | K29: =IF($H29="","",TODAY()-$H29) | Q29: netherlands/2026_08_04_arup_amsterdam_tech_datacenters_pm | R29: Medium | S29: Third Arup Amsterdam open application (open solicitation, not a live vacancy), junior-friendly. Real gap: fluent Dutch required, candidate has none — not disclosed per updated default.
A30: Sweco | B30: Junior Building Physics Consultant – Fire, Environment & Building Physics | C30: Netherlands | D30: Hybrid | F30: Company Site | G30: https://www.sweco.nl/solliciteren/?vacancy=66955 | H30: 46238 | I30: Applied | K30: =IF($H30="","",TODAY()-$H30) | O30: Bas Peeters | P30: bas.peeters@sweco.nl | Q30: netherlands/2026_08_04_sweco_bas_peeters | R30: Low | S30: Real domain mismatch — no daylight/energy/acoustics/fire-safety background at all (different specialization than BIM). Fluent Dutch also required. Applied anyway per explicit user instruction; leans on energy-management coursework + adaptability, gaps not disclosed.
A31: Sweco | B31: Junior Fire Safety Advisor – Fire, Environment & Building Physics | C31: Venlo/Eindhoven, NL | D31: Hybrid | E31: EUR 3,442-4,100/month | F31: Company Site | G31: https://www.sweco.nl/solliciteren/?vacancy=66956 | H31: 46238 | I31: Applied | K31: =IF($H31="","",TODAY()-$H31) | O31: Bas Peeters | P31: bas.peeters@sweco.nl | Q31: netherlands/2026_08_04_sweco_fire_safety_peeters | R31: Low | S31: Same team/manager as the Building Physics Consultant posting; real domain gap (no fire-safety background) plus fluent Dutch required. Applied anyway per established preference for this team; gaps not disclosed.
A32: Sweco | B32: Junior Advisor Cultural Engineering – Environmental and Cultural Engineering Research | C32: Eindhoven, NL | D32: Hybrid | E32: EUR 3,442-4,000/month | F32: Company Site | G32: https://www.sweco.nl/solliciteren/?vacancy=66857 | H32: 46238 | I32: Applied | K32: =IF($H32="","",TODAY()-$H32) | O32: Jules Rutten | P32: jules.rutten@sweco.nl | Q32: netherlands/2026_08_04_sweco_jules_rutten | R32: Medium | S32: Genuine domain fit via real hydrology/water-resources coursework (AutoCAD, HEC-HMS, HEC-RAS) — better fit than the Building Physics/Fire Safety Sweco roles. Dutch C1 required, not disclosed per updated default.
A33: Sweco | B33: (Junior) Architectural BIM Engineer – Logistics and Business Accommodation | C33: De Bilt/Eindhoven/The Hague, NL | D33: Hybrid | E33: EUR 3,750-4,250/month | F33: Company Site | G33: https://www.sweco.nl/solliciteren/?vacancy=66747 | H33: 46238 | I33: Applied | K33: =IF($H33="","",TODAY()-$H33) | O33: Eric Thoma | Q33: netherlands/2026_08_04_sweco_eric_thoma | R33: High | S33: Strong direct BIM match — Revit + multidisciplinary coordination maps closely onto the Guimarães project. Real gaps: 2 years experience, fluent Dutch — not disclosed per updated default.
A34: Sweco | B34: (Junior) Urban Planning Advisor – Urban Projects South (Spatial Development) | C34: Kapelle/Middelburg, NL | D34: Hybrid | E34: EUR 3,600-4,300/month | F34: Company Site | G34: https://www.sweco.nl/solliciteren/?vacancy=66743 | H34: 46238 | I34: Applied | K34: =IF($H34="","",TODAY()-$H34) | O34: Marik Waterman | P34: marik.waterman@sweco.nl | Q34: netherlands/2026_08_04_sweco_marik_waterman | R34: Medium | S34: Surfaced real urban planning coursework (previously untracked). Explicit ask for digitalization/AI experience is a genuine strength. No Dutch requirement listed. 2 years experience gap not disclosed per updated default.
A35: Sweco | B35: (Junior) Transport Pipeline Engineer – Water | C35: De Bilt, NL | D35: Hybrid | E35: EUR 3,600-4,300/month | F35: Company Site | G35: https://www.sweco.nl/solliciteren/?vacancy=66744 | H35: 46238 | I35: Applied | K35: =IF($H35="","",TODAY()-$H35) | O35: John Driessen | P35: john.driessen@sweco.nl | Q35: netherlands/2026_08_04_sweco_john_driessen | R35: Medium | S35: Genuine domain fit via real AutoCAD/ArcGIS/hydrology coursework, matching the posting’s explicit software asks. 1-3 years experience and Dutch C1 gaps not disclosed per updated default.
A36: Sweco | B36: Junior Construction Project Manager – Logistics and Business Accommodation | C36: De Bilt/Amsterdam, NL | D36: Hybrid | E36: EUR 3,500-4,500/month | F36: Company Site | G36: https://www.sweco.nl/solliciteren/?vacancy=66706 | H36: 46238 | I36: Applied | K36: =IF($H36="","",TODAY()-$H36) | P36: lindsay.vanheugten@sweco.nl | Q36: netherlands/2026_08_04_sweco_pm_logistics_thoma | R36: Medium | S36: Same team as the Architectural BIM Engineer application (Eric Thoma). 1-3 years experience and Dutch fluency gaps not disclosed per updated default.
A37: Sweco | B37: Junior Contract Management Advisor – Urban Projects | C37: Rotterdam, NL | D37: Hybrid | E37: EUR 3,442-4,100/month | F37: Company Site | G37: https://www.sweco.nl/solliciteren/?vacancy=66683 | H37: 46238 | I37: Applied | K37: =IF($H37="","",TODAY()-$H37) | O37: Edyta Wisniewska | P37: edyta.wisniewska@sweco.nl | Q37: netherlands/2026_08_04_sweco_edyta_wisniewska | R37: High | S37: Strong match — graduate-entry framing, no Dutch requirement listed, and the FIDIC contract-review internship maps directly onto the role.
A38: Sweco | B38: (Junior) Project Manager – Volantis | C38: Venlo/Eindhoven, NL | D38: Hybrid | F38: Company Site | G38: https://www.sweco.nl/solliciteren/?vacancy=66682 | H38: 46238 | I38: Applied | K38: =IF($H38="","",TODAY()-$H38) | O38: Pim Uiting | P38: pim.uiting@sweco.nl | Q38: netherlands/2026_08_04_sweco_volantis_pim_uiting | R38: Medium | S38: Graduate-friendly ("starters also welcome"). Fluent Dutch and English required, not disclosed per updated default.
A39: Sweco | B39: Junior Soil Consultant – Environmental Consultancy | C39: Groningen, NL | D39: Hybrid | E39: EUR 3,442-4,100/month | F39: Company Site | G39: https://www.sweco.nl/solliciteren/?vacancy=66601 | H39: 46238 | I39: Applied | K39: =IF($H39="","",TODAY()-$H39) | O39: Mariska Moyaert | P39: mariska.moyaert@sweco.nl | Q39: netherlands/2026_08_04_sweco_mariska_moyaert | R39: Medium | S39: Domain-adjacent fit via real hydrology/water-resources/GIS coursework. Recent graduates explicitly welcomed. Dutch gap not disclosed per updated default.
A40: Sweco | B40: Junior Fire Safety Advisor – Fire Safety & Simulations | C40: Amsterdam/Venlo/De Bilt/Rotterdam/Eindhoven, NL | D40: Hybrid | E40: EUR 3,442-4,000/month | F40: Company Site | G40: https://www.sweco.nl/solliciteren/?vacancy=66548 | H40: 46238 | I40: Applied | K40: =IF($H40="","",TODAY()-$H40) | O40: Bart de Vries | P40: bart.devries@sweco.nl | Q40: netherlands/2026_08_04_sweco_bart_de_vries | R40: Low | S40: Same domain gap as the earlier Peeters Fire Safety application (different team: Fire Safety & Simulations). No fire-safety/CFD background. Dutch B2 minimum not disclosed per updated default.
A41: Sweco | B41: Junior Contract Writer Consultant – Civil Engineering (Northern Netherlands) | C41: Groningen/Leeuwarden, NL | D41: Hybrid | E41: EUR 3,442-4,100/month | F41: Company Site | G41: https://www.sweco.nl/solliciteren/?vacancy=65625 | H41: 46238 | I41: Applied | K41: =IF($H41="","",TODAY()-$H41) | O41: Annemarie Rook / Kees van der Molen | P41: annemarie.rook@sweco.nl | Q41: netherlands/2026_08_04_sweco_contract_writer_groningen | R41: High | S41: Strong match — explicit digitalization/AI requirement is a genuine strength, plus the FIDIC contract-review internship. No Dutch requirement listed.
A42: Sweco | B42: Junior Civil Engineering Project Manager – Urban Projects | C42: De Bilt, NL | D42: Hybrid | E42: EUR 3,442-4,000/month | F42: Company Site | G42: https://www.sweco.nl/solliciteren/?vacancy=65797 | H42: 46238 | I42: Applied | K42: =IF($H42="","",TODAY()-$H42) | O42: Bart Witte | P42: bart.witte@sweco.nl | Q42: netherlands/2026_08_04_sweco_pm_urban_projects_witte | R42: Medium | S42: Second application involving Bart Witte as contact (previously Junior BIM Modeller Alkmaar). Fluent Dutch required, not disclosed per updated default.
A43: Sweco | B43: Junior Road Engineering Consultant – Living Environment | C43: Alkmaar, NL | D43: Hybrid | E43: EUR 3,442-4,000/month | F43: Company Site | G43: https://www.sweco.nl/solliciteren/?vacancy=64592 | H43: 46238 | I43: Applied | K43: =IF($H43="","",TODAY()-$H43) | O43: Bart Witte | P43: bart.witte@sweco.nl | Q43: netherlands/2026_08_04_sweco_road_engineering_witte | R43: Medium | S43: Third application to Bart Witte (confirmed with user before proceeding). No specific technical software gap; Dutch C1 required, not disclosed per updated default.
A44: Sweco | B44: Junior Structural Engineer – Engineering & Consultancy Construction | C44: Groningen/Zwolle, NL | D44: Hybrid | E44: EUR 3,442-4,000/month | F44: Company Site | G44: https://www.sweco.nl/solliciteren/?vacancy=63877 | H44: 46238 | I44: Applied | K44: =IF($H44="","",TODAY()-$H44) | O44: Sjaak Schreuder | P44: sjaak.schreuder@sweco.nl | Q44: netherlands/2026_08_04_sweco_sjaak_schreuder | R44: Low | S44: Same domain gap as the Arup Bridge Engineer role — requires structural calculations and Scia/Technosoft, neither of which the candidate has. Dutch gap not disclosed per updated default.
A45: Sweco | B45: Junior BIM Modeler Civil Engineering – Urban Projects | C45: De Bilt, NL | D45: Hybrid | E45: EUR 3,442-4,000/month | F45: Company Site | G45: https://www.sweco.nl/solliciteren/?vacancy=62537 | H45: 46238 | I45: Applied | K45: =IF($H45="","",TODAY()-$H45) | O45: Robin Bree | P45: lindsay.vanheugten@sweco.nl | Q45: netherlands/2026_08_04_sweco_robin_bree | R45: High | S45: Strong direct match (Revit/Civil 3D modelling role). Dutch gap not disclosed per updated default.
A46: Sweco | B46: (Junior) Structural Modeler – Engineering & Consultancy Construction | C46: Groningen, NL | D46: Hybrid | E46: EUR 3,442-4,000/month | F46: Company Site | G46: https://www.sweco.nl/solliciteren/?vacancy=62445 | H46: 46238 | I46: Applied | K46: =IF($H46="","",TODAY()-$H46) | O46: Jasper Pouls | P46: jasper.pouls@sweco.nl | Q46: netherlands/2026_08_04_sweco_jasper_pouls | R46: High | S46: Good direct match (Revit-based modelling role, not pure structural calculation). Dutch gap not disclosed per updated default.
A47: Sweco | B47: Junior Civil Designer – Integrated Infrastructure Design | C47: Amsterdam/De Bilt/Rotterdam/Alkmaar, NL | D47: Hybrid | E47: EUR 3,442-4,000/month | F47: Company Site | G47: https://www.sweco.nl/solliciteren/?vacancy=61191 | H47: 46238 | I47: Applied | K47: =IF($H47="","",TODAY()-$H47) | O47: Peter Koelman | P47: peter.koelman@sweco.nl | Q47: netherlands/2026_08_04_sweco_peter_koelman | R47: High | S47: Strong match — no Dutch requirement listed, explicit AI/digitalization emphasis is a genuine strength.
A48: Sweco | B48: (Junior) Civil Engineering Project Engineer – Infrastructure | C48: Zwolle, NL | D48: Hybrid | E48: EUR 3,442-4,000/month | F48: Company Site | G48: https://www.sweco.nl/solliciteren/?vacancy=55138 | H48: 46238 | I48: Applied | K48: =IF($H48="","",TODAY()-$H48) | O48: Jeroen van de Uitvlugt | P48: jeroen.vandeuitvlugt@sweco.nl | Q48: netherlands/2026_08_04_sweco_jeroen_uitvlugt | R48: High | S48: Strong match — no Dutch requirement listed; AutoCAD, cost estimation and FIDIC contract-review experience all genuine strengths.
A49: Sweco | B49: Junior Road Management Advisor | C49: Multiple NL offices (Middelburg/Groningen/Arnhem/Leeuwarden/De Bilt/Rotterdam/Alkmaar/Eindhoven/Amsterdam) | D49: Hybrid | F49: Company Site | G49: https://www.sweco.nl/solliciteren/?vacancy=52972 | H49: 46238 | I49: Applied | K49: =IF($H49="","",TODAY()-$H49) | O49: Rob Krom | P49: rob.krom@sweco.nl | Q49: netherlands/2026_08_04_sweco_rob_krom | R49: High | S49: Strong match — no Dutch requirement listed; GIS (ArcGIS) and explicit AI/digitalization asks are both genuine strengths.
A50: Sweco | B50: (Junior) Hydraulic Engineering Design Manager – Structural Hydraulic Engineering | C50: De Bilt/Rotterdam/Amsterdam, NL | D50: Hybrid | E50: EUR 4,000-5,500/month | F50: Company Site | G50: https://www.sweco.nl/solliciteren/?vacancy=50518 | H50: 46238 | I50: Applied | K50: =IF($H50="","",TODAY()-$H50) | O50: Jan Hein Poodt | P50: jan-hein.poodt@sweco.nl | Q50: netherlands/2026_08_04_sweco_jan_hein_poodt | R50: Low | S50: Long-shot per user request — 5 years experience required despite "(Junior)" title, mid-level salary band. Good domain fit (hydrology/water resources coursework) but real seniority gap.
A51: Sweco | B51: Junior Advisor Underground Infrastructure & Water | C51: De Bilt, NL | D51: Hybrid | E51: EUR 3,442-3,766/month | F51: Company Site | G51: https://www.sweco.nl/solliciteren/?vacancy=47996 | H51: 46238 | I51: Applied | K51: =IF($H51="","",TODAY()-$H51) | O51: John Driessen | P51: john.driessen@sweco.nl | Q51: netherlands/2026_08_04_sweco_underground_infra_driessen | R51: High | S51: Second application to John Driessen (previously Transport Pipeline Engineer). Strong match — GIS/data science/BIM explicitly named, no Dutch requirement listed, graduate-friendly.
A52: Sweco | B52: (Junior) Structural Engineer – Engineering & Consultancy Construction | C52: Middelburg, NL | D52: Hybrid | E52: EUR 3,442-4,000/month | F52: Company Site | G52: https://www.sweco.nl/solliciteren/?vacancy=53226 | H52: 46238 | I52: Applied | K52: =IF($H52="","",TODAY()-$H52) | O52: Michel van Aert | P52: michel.vanaert@sweco.nl | Q52: netherlands/2026_08_04_sweco_michel_van_aert | R52: High | S52: Same shape as the Schreuder/Pouls structural roles (Revit-based modelling, different branch). Dutch gap not disclosed per updated default.
A53: Sweco | B53: Junior Project Consultant – Area Development | C53: Arnhem, NL | D53: Hybrid | E53: EUR 3,442-4,000/month | F53: Company Site | G53: https://www.sweco.nl/solliciteren/?vacancy=39914 | H53: 46238 | I53: Applied | K53: =IF($H53="","",TODAY()-$H53) | O53: Marcel Janssen | P53: marcel.janssen@sweco.nl | Q53: netherlands/2026_08_04_sweco_marcel_janssen | R53: High | S53: Good match — digitalization/AI explicitly a plus, civil engineering/land-water framing fits. Dutch gap not disclosed per updated default.
A54: Sweco | B54: (Junior) Civil Engineer – Engineering and Urban Projects | C54: Multiple NL offices (Alkmaar/Amsterdam/Middelburg/Arnhem/Groningen/Zwolle/Leeuwarden/De Bilt) | D54: Hybrid | E54: EUR 3,442-4,000/month | F54: Company Site | G54: https://www.sweco.nl/solliciteren/?vacancy=39949 | H54: 46238 | I54: Applied | K54: =IF($H54="","",TODAY()-$H54) | O54: Robin Bree | P54: lindsay.vanheugten@sweco.nl | Q54: netherlands/2026_08_04_sweco_civil_engineer_bree | R54: High | S54: Second application to Robin Bree (previously BIM Modeler Civil Engineering). Strong overall match: AutoCAD, digitalization/AI, FIDIC contract review all genuine strengths.
A55: Sweco Energi | B55: Junior Project Manager – District Heating Projects | C55: Greater Copenhagen / North Zealand, DK | F55: Company Site | G55: https://candidate.hr-manager.net/ApplicationInit.aspx?cid=87&ProjectId=183677&DepartmentId=2127&SkipAdvertisement=true | H55: 46238 | I55: Applied | K55: =IF($H55="","",TODAY()-$H55) | Q55: denmark/2026_08_04_sweco_district_heating_pm | R55: Medium | S55: 3 years experience required, not disclosed per updated default. No explicit language requirement listed. Leans on real energy-management coursework.
A56: Sweco | B56: Junior Engineer (Req. 269) | C56: Multiple BE/LU offices (Berchem/Gent/Brussels/Hasselt/Leuven and others) | D56: Hybrid | F56: Company Site | H56: 46238 | I56: Applied | K56: =IF($H56="","",TODAY()-$H56) | Q56: belgium/2026_08_04_sweco_junior_engineer | R56: High | S56: No language/software requirement listed, explicitly open to near-graduates. Excellent accessibility, strong AI/digitalization profile fits well.
A57: Sweco | B57: BIM Coordinator (Req. 1359) | C57: Antwerp, BE (also Ghent/Berchem/Brussels and others) | D57: Hybrid | F57: Company Site | H57: 46238 | I57: Applied | K57: =IF($H57="","",TODAY()-$H57) | Q57: belgium/2026_08_04_sweco_bim_coordinator_antwerp | R57: High | S57: Strong direct BIM match. 3 years experience gap not disclosed per updated default; no language requirement listed.
A58: Sweco | B58: Information Coordinator (expression of interest) | C58: Sundsvall/Ostersund, SE | D58: Hybrid | F58: Company Site | G58: https://www.sweco.se/karriar/ansok-har/?rmpage=apply&rmjob=25028 | H58: 46238 | I58: Applied | K58: =IF($H58="","",TODAY()-$H58) | O58: Malin Kullstrom | P58: malin.kullstrom@sweco.se | Q58: sweden/2026_08_04_sweco_info_coordinator_sundsvall | R58: High | S58: Excellent domain fit — role is essentially the candidate’s exact specialty (Information Manager, ISO 19650). Swedish gap not disclosed per updated default; confirmed with user given the strong fit. 3 years experience also required.
A59: WSP | B59: Junior Water Safety Advisor – Water and Environment | C59: Breda/Nieuwegein/Rotterdam, NL | D59: Hybrid | F59: Company Site | H59: 46238 | I59: Applied | K59: =IF($H59="","",TODAY()-$H59) | Q59: netherlands/2026_08_04_wsp_water_safety | R59: Medium | S59: First WSP application. Decent water-adjacent fit; geotechnical stability/piping analysis is a different specialty than hydrology coursework, framed honestly as genuine interest rather than claimed expertise.
A60: Ferrovial Construction | B60: BIM Graduate – Quality and Design Department (JR18626) | C60: London, UK | D60: On-site | F60: Company Site | G60: https://ferrovial.wd3.myworkdayjobs.com/Ferrovial_Career_Site/job/London/BIM-Graduate_JR18626/apply?source=LinkedIn | H60: 46246 | I60: Applied | K60: =IF($H60="","",TODAY()-$H60) | Q60: uk/2026_08_12_ferrovial_bim_graduate | R60: High | S60: Near-exact fit (posting names BIM as a qualifying master’s degree, 2-year graduate program, no experience required). UK right-to-work confirmed by user as securable by start date; stated directly on the CV per the posting’s essential requirement.
A61: Ferrovial Construction | B61: Graduate Digital Construction & Data Management 2026 (JR18262) | C61: London, UK | D61: On-site | F61: Company Site | G61: https://ferrovial.wd3.myworkdayjobs.com/en-US/Ferrovial_Career_Site/job/London/Graduate-Digital-Construction---Data-Management-2026_JR18262/apply?source=LinkedIn | H61: 46246 | I61: Applied | K61: =IF($H61="","",TODAY()-$H61) | Q61: uk/2026_08_12_ferrovial_digital_construction_data | R61: High | S61: Second Ferrovial application, same team/program as BIM Graduate (JR18626). UK right-to-work confirmed manageable by user, stated directly on CV.
A62: Graitec | B62: AEC Prototyping Engineer | C62: Paris, FR | F62: Company Site | H62: 46246 | I62: Applied | K62: =IF($H62="","",TODAY()-$H62) | Q62: france/2026_08_12_graitec_aec_prototyping | R62: High | S62: Exceptional fit — combines both core specialties (AEC/BIM and AI/agentic systems). BIMGraphExplorer is an almost literal match to the role’s rapid-prototyping/validation cycle. No French requirement listed.
A63: Mott MacDonald | B63: BIM Engineer (Structural BIM), Energy unit (Job Ref 15395) | C63: Sofia, BG | D63: Hybrid | F63: Company Site | G63: https://career2.successfactors.eu/career?company=MMPROD&lang=en_150&login_ns=register&career_ns=job_application&career_job_req_id=15395&jobPipeline=CareerSite&codes=EXT | H63: 46250 | I63: Applied | K63: =IF($H63="","",TODAY()-$H63) | O63: Maria Cervantes | Q63: bulgaria/2026_08_16_mott_macdonald_bim_sofia | R63: Medium | S63: Structural-engineering degree gap not disclosed per updated default; actual day-to-day tasks (ACC, ISO 19650, clash detection) map very well to real strengths.
A64: AECOM | B64: BIM & Digital Specialist / Digital Project Delivery Engineer (Req J10154523) | C64: Madrid, ES | D64: Hybrid | F64: Company Site | H64: 46250 | I64: Applied | K64: =IF($H64="","",TODAY()-$H64) | Q64: spain/2026_08_16_aecom_bim_digital_madrid | R64: Medium | S64: Good BIM+data/automation fit (similar shape to Graitec). 2-5 years experience and Power Platform/Azure gaps not disclosed per updated default; no Spanish requirement stated, only English.
A65: King and Moffatt Building Services | B65: Engineering Graduate Programme | C65: Carrick-on-Shannon, Co. Leitrim, IE | D65: On-site | F65: Company Site | H65: 46250 | I65: Applied | K65: =IF($H65="","",TODAY()-$H65) | Q65: ireland/2026_08_16_king_moffatt_engineering_graduate | R65: Low | S65: Ireland work-authorization status unresolved — user asked to omit any mention either way, to be sorted out separately. Also a degree-field mismatch (M&E/Building Services vs Civil), bridged via the programme’s Design/BIM rotation.
A66: DBFL Consulting Engineers | B66: Graduate Development Programme | C66: Dublin, IE | F66: Company Site | H66: 46250 | I66: Applied | K66: =IF($H66="","",TODAY()-$H66) | Q66: ireland/2026_08_16_dbfl_graduate_programme | R66: Medium | S66: Strong degree-field match (pure Civil Engineering). Same unresolved Ireland work-authorization question as King and Moffatt; omitted from CV per user instruction.
A67: TwinMaster | B67: Product Manager (Arch-e platform) | C67: Remote | D67: Remote | F67: Networking | H67: 46250 | I67: Applied | K67: =IF($H67="","",TODAY()-$H67) | O67: Michael | P67: michael@thetwinmaster.com | Q67: remote/2026_08_16_twinmaster_product_manager | R67: Low | S67: Categorical mismatch (Licensed Architect, 7 years, Architect of Record required). Sent as an openly self-aware networking note rather than a standard tailored pitch, per explicit user direction.
A68: BAM Building | B68: BIM Coordinator (Digital Project Solutions) | C68: Waterford, IE | F68: Company Site | H68: 46250 | I68: Applied | K68: =IF($H68="","",TODAY()-$H68) | Q68: ireland/2026_08_16_bam_bim_coordinator_waterford | R68: High | S68: Excellent direct match — ISO 19650/CDE/MIDP-TIDP is the candidate’s core specialty. Same unresolved Ireland work-authorization question as King and Moffatt/DBFL; omitted from CV per user instruction.
A69: Hurks (Ballast Nedam) | B69: BIM Coordinator | C69: Eindhoven, NL | D69: On-site | E69: EUR 3,989-5,699/month | F69: LinkedIn | H69: 46250 | I69: Applied | K69: =IF($H69="","",TODAY()-$H69) | O69: Anneke den Haan | Q69: netherlands/2026_08_16_hurks_ballast_nedam_bim | R69: Medium | S69: LinkedIn flagged this as a "low" match (missing years of experience, specific tools: Solibri/BIMcollab Nexus/Dalux, Dutch fluency). Not disclosed per updated default; leans on genuine BIM/ISO19650/AI overlap.
A70: REM d.o.o. | B70: Designer-Developer (product design/development) | C70: Trebnje, SI | F70: Job Board | H70: 46251 | I70: Applied | K70: =IF($H70="","",TODAY()-$H70) | Q70: slovenia/2026_08_17_rem_doo_trebnje | R70: High | S70: Good fit for modular building systems manufacturer. Revit explicitly named; English satisfies language requirement (no Slovene needed). 2 years experience gap not disclosed per updated default.
A71: Pilon AEC | B71: Open application – BIM specialist | C71: Ljubljana, SI | F71: Networking | G71: https://www.pilon.si/ | H71: 46251 | I71: Applied | K71: =IF($H71="","",TODAY()-$H71) | P71: info@pilon.si | Q71: slovenia/2026_08_17_pilon_open_application | R71: High | S71: Genuine speculative pitch to a real BIM software company (Archicad/MEP Designer/DDScad distributor). Stronger fit than Atrij/Saning since Pilon’s core business is BIM. No named contact or careers page found.
A72: Geoservis d.o.o. | B72: Open application – BIM and geospatial background | C72: Ljubljana, SI | F72: Networking | G72: https://geoservis.si/ | H72: 46251 | I72: Applied | K72: =IF($H72="","",TODAY()-$H72) | P72: info@geoservis.si | Q72: slovenia/2026_08_17_geoservis_open_application | R72: Medium | S72: Speculative pitch to a Leica Geosystems surveying/3D-scanning equipment distributor. Genuine fit via real scan-to-BIM point-cloud coursework and ArcGIS. No named contact or careers page found.
A73: BIMING (Epoha d.o.o.) | B73: Open application – scan-to-BIM background | C73: Ljubljana, SI | F73: Networking | G73: https://biming.si/ | H73: 46251 | I73: Applied | K73: =IF($H73="","",TODAY()-$H73) | O73: Gregor Novakovic | P73: info@epoha.si | Q73: slovenia/2026_08_17_biming_gregor_novakovic | R73: High | S73: Exceptional fit — BIMING’s core business (point-cloud to BIM conversion) almost literally matches the candidate’s scan-to-BIM coursework. Addressed to named CEO.
A74: Hilti | B74: Technical Engineer (Req. 18545) | C74: Trzin, SI | F74: Company Site | G74: https://careers.hilti.group/en/jobs/ | H74: 46251 | I74: Applied | K74: =IF($H74="","",TODAY()-$H74) | Q74: slovenia/2026_08_17_hilti_technical_engineer | R74: Medium | S74: General civil-engineering technical-consulting fit, not BIM-specific. Driving license omitted per standing instruction; 2 years experience gap not disclosed per updated default.
A75: ELES, d.o.o. | B75: Administrator skupnega podatkovnega okolja (CDE/Dalux Administrator) — student work | C75: Ljubljana (Bericevo), SI | F75: Job Board | G75: https://www.eles.si/ | H75: 46253 | I75: Applied | K75: =IF($H75="","",TODAY()-$H75) | Q75: slovenia/2026_08_19_eles_cde_administrator | R75: High | S75: Strong fit: student role administering the CDE (Dalux) for an active BIM implementation project, explicitly targeting BIM-trained master's students. Profile led with CDE administration and ISO 19650 EIR validation experience.
A76: Winthrop Technologies | B76: BIM Technician (MEP bias) | C76: Ballymount, Dublin 22, IE | D76: Office-based (5 days/week) | F76: Company Site | H76: 46253 | I76: Applied | K76: =IF($H76="","",TODAY()-$H76) | Q76: ireland/2026_08_19_winthrop_bim_technician | R76: Medium | S76: Genuine tools fit (Revit, AutoCAD, MEP clash detection, ISO 19650 EIR), but posting asks for 2 years' MEP BIM experience and Navisworks, which are gaps not disclosed per standing policy.
A77: Winthrop Technologies | B77: Graduate CSA Engineer 2026 | C77: Dublin, IE | F77: Company Site | H77: 46253 | I77: Applied | K77: =IF($H77="","",TODAY()-$H77) | Q77: ireland/2026_08_19_winthrop_graduate_csa | R77: High | S77: Strong graduate-programme fit: civil engineering degree plus drawing-review and design-coordination experience map directly onto CSA responsibilities. Second application to Winthrop (also applied to BIM Technician role).
A78: Confidential (family-owned technical installer) | B78: Junior Project Leader Techniques | C78: Poperinge, BE | F78: Job Board | H78: 46255 | I78: Applied | K78: =IF($H78="","",TODAY()-$H78) | Q78: belgium/2026_08_21_poperinge_junior_project_leader | R78: Low | S78: Long-shot: client-facing HVAC/technical PM role in West Flanders, likely requires Dutch which the candidate does not have. Applied at user's request with cover letter transparent about English working language and commitment to learn Dutch.
A79: Drees & Sommer | B79: (Junior) BIM Manager (m/f/d) | C79: Leipzig, DE | F79: Company Site | G79: https://jobs.smartrecruiters.com/DreesSommerSE/744000133970415--junior-bim-manager-w-m-d- | H79: 46259 | I79: Applied | K79: =IF($H79="","",TODAY()-$H79) | Q79: germany/2026_08_25_drees_sommer_junior_bim_manager | R79: High | S79: Strong entry-level fit: BIM methodology implementation, cross-discipline coordination, and stakeholder-facing communication line up directly with the role. No photo included (standing gap, confirmed with user, no asset available).
A80: CYPE | B80: BIM Software Developer (R&D / interoperability, referral) | C80: Alicante, ES | F80: Referral | H80: 46261 | I80: Applied | K80: =IF($H80="","",TODAY()-$H80) | Q80: spain/2026_08_27_cype_bim_software_referral | R80: High | S80: Warm personal referral from an outgoing employee (R&D on Horizon/LIFE EU projects plus BIM software interoperability with Revit). CV tailored toward software side (IfcToNeo4j, BIMGraphExplorer, Headstarter AI fellowship, in-progress That Open Company BIM software dev programme). No formal job posting/link.
A81: Archnetix | B81: BIM tooling / automation developer (speculative) | C81: Islamabad, PK | F81: Referral | G81: https://www.archnetix.com/ | I81: To Apply | K81: =IF($H81="","",TODAY()-$H81) | M81: Reach out to CEO via warm connection | Q81: pakistan/2026_09_13_archnetix_bim_tooling | R81: High | S81: Dubai-HQ BIM services firm (Scan-to-BIM, coordination, archviz) with main production office in Bahria Town, Islamabad. Targeting the Islamabad office only; user does not want the UAE. They advertise no in-house software development, so the pitch is building tools/automation on top of their BIM models and data. Warm CEO connection is the route in. CV built; no message drafted yet.
A82: FirstClass d.o.o. (recruiter) | B82: Sales Engineer (formwork and scaffolding) | C82: Ljubljana, SI / field across Slovenia | D82: On-site | F82: Recruiter | H82: 46285 | I82: Applied | K82: =IF($H82="","",TODAY()-$H82) | Q82: slovenia/2026_09_20_firstclass_sales_engineer | R82: Medium | S82: End client not named: an international formwork and scaffolding company. Career pivot toward technical sales, so the CV drops the software/AI material and leads on construction, FIDIC contract exposure and 5D cost estimation. Posting asks for 1-3 years experience. Category B licence stated on the CV; user confirmed they hold one.
A83: Spar Slovenija d.o.o. | B83: Facilities Maintenance Coordinator | C83: Ljubljana, SI | D83: Hybrid | F83: Job Board | H83: 46285 | I83: Applied | K83: =IF($H83="","",TODAY()-$H83) | Q83: slovenia/2026_09_20_spar_facilities_coordinator | R83: Medium | S83: Centralising maintenance across 100 Spar stores and 13 Interspar centres. Education far exceeds the 5th-level minimum; energy management coursework maps to the building energy duty, 5D cost estimation to cost analyses, FIDIC internship to tenders/orders/contracts. Category B licence stated for branch inspections. Slovene A1 is the main soft risk.
A84: Iskra d.o.o. | B84: Order and production coordinator (customers/sales/logistics link) | C84: Slovenia (Kranj / Ljubljana area) | F84: Job Board | G84: https://www.iskra.si/ | H84: 46285 | I84: Applied | K84: =IF($H84="","",TODAY()-$H84) | Q84: slovenia/2026_09_20_iskra_order_coordinator | R84: Low | S84: Long-shot, flagged to user before building. Posting wants economics/commerce/logistics education capped at VI/2, 1-3 years experience, and lists ERP, logistics and transport organisation as advantages, none of which the candidate has. Built on transferable coordination, FIDIC document review, process modelling and cost analysis instead.
A85: Sumer d.o.o. | B85: Technical documentation / production technologist | C85: Slovenia | F85: Job Board | G85: http://www.sumer.si/ | H85: 46285 | I85: Applied | K85: =IF($H85="","",TODAY()-$H85) | Q85: slovenia/2026_09_20_sumer_technical_documentation | R85: Low | S85: Long-shot, flagged before building. Plastics injection moulding manufacturer; core duties (injection programs, tool testing, first-piece approval under ISO/TS 16949, production time norms, mechanical working drawings) need mechanical/moulding training the candidate lacks. Stated expectations are only behavioural, which is the one opening. Built on document control, cost estimation, quality validation and supplier checking.
A86: HRM solutions d.o.o. (recruiter) | B86: Constructor / mechanical design engineer (aerospace client) | C86: Slovenia | E86: EUR 2,200 - 2,500 gross/month | F86: Recruiter | G86: https://hrm-resitve.si/ | H86: 46285 | I86: Applied | K86: =IF($H86="","",TODAY()-$H86) | M86: Consider a separate speculative registration with this agency for BIM/construction roles | Q86: slovenia/2026_09_20_hrm_solutions_constructor | R86: Low | S86: Weakest fit of the 20 Sep batch, flagged before building. Posting explicitly requires a mechanical engineering degree and states 3 years experience as mandatory; salary band indicates they are buying experience. End client is in aerospace. Built on 3D modelling from 2D drawings, quantity take-off as BOM analog, and document approval workflows. Agency is worth a separate speculative approach in the candidate's actual field.
A87: SZ-Infrastruktura d.o.o. (Slovenske zeleznice) | B87: Professional Associate I, NOC GSM-R supervision (ref. 180/26) | C87: Ljubljana, SI | D87: On-site | F87: Company Site | G87: https://www.sz.si/kariera/ | H87: 46285 | I87: Applied | K87: =IF($H87="","",TODAY()-$H87) | N87: 46288 | Q87: slovenia/2026_09_20_sz_infrastruktura_noc_gsmr | R87: Medium | S87: Posting deadline 23 Sep 2026; 2 positions. Best of the 20 Sep batch after Spar: education condition says relevant field with electrical engineering only preferred, experience bar is 12 months, and selected candidates are trained for the telecoms technician qualification. Hooks: maintenance process coordination/optimisation and technical bases for tenders. Gaps: no telecom/EE background, no 12 months similar experience. Fixed-term 1 year with 4-month probation.
A88: Mercor | B88: AI Safety Expert, red teaming (English & Urdu) | C88: Remote | D88: Remote | E88: USD 16 - 22/hour, contractor | F88: Job Board | H88: 46295 | I88: Applied | K88: =IF($H88="","",TODAY()-$H88) | Q88: remote/2026_09_30_mercor_ai_safety_red_team | R88: High | S88: Best substantive fit to date: the MSc thesis is itself a systematic LLM evaluation study (validated judge, matched conditions, 23 datasets, 367 questions, prompt-design ablation), which is the methodology this role wants. Urdu native fluency is the hard gate and was confirmed for the first time on this date. English corrected to C2 from the understated C1 used on all prior CVs. Gaps: no formal red teaming or cybersecurity background, both listed only as nice-to-have. Independent contractor engagement, weekly Stripe/Wise.
A89: Brickborne | B89: BIM specialist / Revit modelling (speculative, no posting) | C89: California, USA (remote) | D89: Remote | F89: Company Site | G89: https://brickborne.com/ | I89: To Apply | K89: =IF($H89="","",TODAY()-$H89) | M89: Send speculative outreach to founder Hamza Khan (shared NUST alma mater) | O89: Hamza Khan (founder/CEO) | Q89: usa/2026_10_08_brickborne_bim_specialist | R89: Medium | S89: Small founder-led drafting/BIM firm, no careers page, so speculative. Services: permit drawings, construction documentation, CAD drafting, BIM modelling, scan-to-BIM, MEP/HVAC drawings, rendering, quantity surveying. Stack Revit/AutoCAD/Navisworks. Founder Hamza Khan is a NUST civil engineering graduate, same alma mater, which is the warm hook for outreach. Gaps: no Navisworks and no rendering/visualisation tools, both left unclaimed. CV built; outreach message not yet written.
K90: =IF($H90="","",TODAY()-$H90)
K91: =IF($H91="","",TODAY()-$H91)
K92: =IF($H92="","",TODAY()-$H92)
K93: =IF($H93="","",TODAY()-$H93)
K94: =IF($H94="","",TODAY()-$H94)
K95: =IF($H95="","",TODAY()-$H95)
K96: =IF($H96="","",TODAY()-$H96)
K97: =IF($H97="","",TODAY()-$H97)
K98: =IF($H98="","",TODAY()-$H98)
K99: =IF($H99="","",TODAY()-$H99)
K100: =IF($H100="","",TODAY()-$H100)
...

Sheet Lists
A1: Stage | B1: Outcome | C1: Work Setup | D1: Source | E1: Priority | G1: Edit these lists to change the dropdown options on the Applications tab.
A2: To Apply | B2: Rejected | C2: Remote | D2: LinkedIn | E2: High
A3: Applied | B3: Ghosted | C3: Hybrid | D3: Company Site | E3: Medium
A4: Phone Screen | B4: Withdrawn | C4: On-site | D4: Referral | E4: Low
A5: Interview | B5: Offer Accepted | D5: Recruiter
A6: Final Round | B6: Offer Declined | D6: Indeed
A7: Offer | D7: Glassdoor
D8: Job Board
D9: Networking
D10: Other
